.flake8
.gitignore
LICENSE.md
MANIFEST.in
Makefile
README.md
biovis-media-extension.code-workspace
requirements.txt
setup.cfg
setup.py
biovis_media_extension/.DS_Store
biovis_media_extension/__init__.py
biovis_media_extension/config.py
biovis_media_extension/convertor.py
biovis_media_extension/docker_mgmt.py
biovis_media_extension/exceptions.py
biovis_media_extension/extension.py
biovis_media_extension/file_mgmt.py
biovis_media_extension/models.py
biovis_media_extension/plugin.py
biovis_media_extension/process_mgmt.py
biovis_media_extension/request_mgmt.py
biovis_media_extension/schema.py
biovis_media_extension/syntax_parser.py
biovis_media_extension/utils.py
biovis_media_extension/version.py
biovis_media_extension/convertors/__init__.py
biovis_media_extension/lib/ossutil64
biovis_media_extension/lib/ossutilmac64
biovis_media_extension/plugins/.DS_Store
biovis_media_extension/plugins/__init__.py
biovis_media_extension/static/default.css
biovis_media_extension/static/bokeh/bokeh-1.0.4.min.js
biovis_media_extension/static/bokeh/bokeh-gl-1.0.4.min.js
biovis_media_extension/static/bokeh/bokeh-tables-1.0.4.min.js
biovis_media_extension/static/bokeh/bokeh-widgets-1.0.4.min.js
biovis_media_extension/templates/help_doc_template.html
biovis_media_extension/templates/plugin/index.html
biovis_media_extension/templates/plugin/css/bootstrap.min.css
biovis_media_extension/templates/plugin/css/font-awesome.min.css
biovis_media_extension/templates/plugin/fonts/FontAwesome.otf
biovis_media_extension/templates/plugin/fonts/fontawesome-webfont.eot
biovis_media_extension/templates/plugin/fonts/fontawesome-webfont.svg
biovis_media_extension/templates/plugin/fonts/fontawesome-webfont.ttf
biovis_media_extension/templates/plugin/fonts/fontawesome-webfont.woff
biovis_media_extension/templates/plugin/fonts/fontawesome-webfont.woff2
biovis_media_extension/templates/plugin/fonts/glyphicons-halflings-regular.eot
biovis_media_extension/templates/plugin/fonts/glyphicons-halflings-regular.svg
